scrapga/__init__.py
scrapga/api.py
scrapga-0.0.7.dist-info/METADATA
scrapga-0.0.7.dist-info/WHEEL
scrapga-0.0.7.dist-info/top_level.txt
scrapga-0.0.7.dist-info/RECORD
