Metadata-Version: 2.1
Name: scrapga
Version: 0.0.7
Summary: GSMArena Scraper
Home-page: https://isdow.com
Author: dow
Author-email: dow@isdow.com
License: MIT
Platform: UNKNOWN
Requires-Python: >=3.6
Requires-Dist: beautifulsoup4
Requires-Dist: requests
